<annotation>
	<folder>synthetic_data</folder>
	<filename>224.jpg</filename>
	<path>../dataset/synthetic_data/images/224.jpg</path>
	<source>
		<database>Source</database>
	</source>
	<segmented>0</segmented>
	<size>
		<width>600</width>
		<height>800</height>
		<depth>3</depth>
	</size>
	<object>
		<name>Bee</name>
		<pose>Front</pose>
		<truncated>0</truncated>
		<bndbox>
			<xmin>82</xmin>
			<ymin>181</ymin>
			<xmax>134</xmax>
			<ymax>249</ymax>
		</bndbox>
	</object>
	<object>
		<name>Bee</name>
		<pose>Front</pose>
		<truncated>0</truncated>
		<bndbox>
			<xmin>106</xmin>
			<ymin>506</ymin>
			<xmax>199</xmax>
			<ymax>574</ymax>
		</bndbox>
	</object>
	<object>
		<name>Bee</name>
		<pose>Front</pose>
		<truncated>0</truncated>
		<bndbox>
			<xmin>122</xmin>
			<ymin>2</ymin>
			<xmax>202</xmax>
			<ymax>103</ymax>
		</bndbox>
	</object>
	<object>
		<name>Bee</name>
		<pose>Front</pose>
		<truncated>0</truncated>
		<bndbox>
			<xmin>84</xmin>
			<ymin>646</ymin>
			<xmax>195</xmax>
			<ymax>740</ymax>
		</bndbox>
	</object>
	<object>
		<name>Bee</name>
		<pose>Front</pose>
		<truncated>0</truncated>
		<bndbox>
			<xmin>402</xmin>
			<ymin>364</ymin>
			<xmax>569</xmax>
			<ymax>526</ymax>
		</bndbox>
	</object>
	<object>
		<name>Bee</name>
		<pose>Front</pose>
		<truncated>0</truncated>
		<bndbox>
			<xmin>388</xmin>
			<ymin>117</ymin>
			<xmax>555</xmax>
			<ymax>279</ymax>
		</bndbox>
	</object>
	<object>
		<name>Bee</name>
		<pose>Front</pose>
		<truncated>0</truncated>
		<bndbox>
			<xmin>180</xmin>
			<ymin>390</ymin>
			<xmax>342</xmax>
			<ymax>557</ymax>
		</bndbox>
	</object>
</annotation>