<annotation>
	<folder>synthetic_data</folder>
	<filename>258.jpg</filename>
	<path>../dataset/synthetic_data/images/258.jpg</path>
	<source>
		<database>Source</database>
	</source>
	<segmented>0</segmented>
	<size>
		<width>984</width>
		<height>1024</height>
		<depth>3</depth>
	</size>
	<object>
		<name>Bee</name>
		<pose>Front</pose>
		<truncated>0</truncated>
		<bndbox>
			<xmin>837</xmin>
			<ymin>188</ymin>
			<xmax>948</xmax>
			<ymax>282</ymax>
		</bndbox>
	</object>
	<object>
		<name>Bee</name>
		<pose>Front</pose>
		<truncated>0</truncated>
		<bndbox>
			<xmin>294</xmin>
			<ymin>150</ymin>
			<xmax>362</xmax>
			<ymax>243</ymax>
		</bndbox>
	</object>
	<object>
		<name>Bee</name>
		<pose>Front</pose>
		<truncated>0</truncated>
		<bndbox>
			<xmin>400</xmin>
			<ymin>256</ymin>
			<xmax>468</xmax>
			<ymax>308</ymax>
		</bndbox>
	</object>
	<object>
		<name>Bee</name>
		<pose>Front</pose>
		<truncated>0</truncated>
		<bndbox>
			<xmin>511</xmin>
			<ymin>254</ymin>
			<xmax>605</xmax>
			<ymax>365</ymax>
		</bndbox>
	</object>
	<object>
		<name>Bee</name>
		<pose>Front</pose>
		<truncated>0</truncated>
		<bndbox>
			<xmin>597</xmin>
			<ymin>507</ymin>
			<xmax>708</xmax>
			<ymax>601</ymax>
		</bndbox>
	</object>
	<object>
		<name>Bee</name>
		<pose>Front</pose>
		<truncated>0</truncated>
		<bndbox>
			<xmin>71</xmin>
			<ymin>257</ymin>
			<xmax>116</xmax>
			<ymax>323</ymax>
		</bndbox>
	</object>
	<object>
		<name>Bee</name>
		<pose>Front</pose>
		<truncated>0</truncated>
		<bndbox>
			<xmin>615</xmin>
			<ymin>112</ymin>
			<xmax>681</xmax>
			<ymax>157</ymax>
		</bndbox>
	</object>
	<object>
		<name>Bee</name>
		<pose>Front</pose>
		<truncated>0</truncated>
		<bndbox>
			<xmin>910</xmin>
			<ymin>508</ymin>
			<xmax>984</xmax>
			<ymax>589</ymax>
		</bndbox>
	</object>
	<object>
		<name>Bee</name>
		<pose>Front</pose>
		<truncated>0</truncated>
		<bndbox>
			<xmin>827</xmin>
			<ymin>920</ymin>
			<xmax>907</xmax>
			<ymax>997</ymax>
		</bndbox>
	</object>
	<object>
		<name>Bee</name>
		<pose>Front</pose>
		<truncated>0</truncated>
		<bndbox>
			<xmin>432</xmin>
			<ymin>161</ymin>
			<xmax>477</xmax>
			<ymax>227</ymax>
		</bndbox>
	</object>
	<object>
		<name>Bee</name>
		<pose>Front</pose>
		<truncated>0</truncated>
		<bndbox>
			<xmin>9</xmin>
			<ymin>46</ymin>
			<xmax>75</xmax>
			<ymax>91</ymax>
		</bndbox>
	</object>
	<object>
		<name>Bee</name>
		<pose>Front</pose>
		<truncated>0</truncated>
		<bndbox>
			<xmin>599</xmin>
			<ymin>413</ymin>
			<xmax>667</xmax>
			<ymax>506</ymax>
		</bndbox>
	</object>
	<object>
		<name>Bee</name>
		<pose>Front</pose>
		<truncated>0</truncated>
		<bndbox>
			<xmin>324</xmin>
			<ymin>308</ymin>
			<xmax>417</xmax>
			<ymax>376</ymax>
		</bndbox>
	</object>
	<object>
		<name>Bee</name>
		<pose>Front</pose>
		<truncated>0</truncated>
		<bndbox>
			<xmin>824</xmin>
			<ymin>687</ymin>
			<xmax>926</xmax>
			<ymax>802</ymax>
		</bndbox>
	</object>
	<object>
		<name>Bee</name>
		<pose>Front</pose>
		<truncated>0</truncated>
		<bndbox>
			<xmin>380</xmin>
			<ymin>782</ymin>
			<xmax>454</xmax>
			<ymax>864</ymax>
		</bndbox>
	</object>
	<object>
		<name>Bee</name>
		<pose>Front</pose>
		<truncated>0</truncated>
		<bndbox>
			<xmin>914</xmin>
			<ymin>890</ymin>
			<xmax>966</xmax>
			<ymax>958</ymax>
		</bndbox>
	</object>
	<object>
		<name>Bee</name>
		<pose>Front</pose>
		<truncated>0</truncated>
		<bndbox>
			<xmin>901</xmin>
			<ymin>681</ymin>
			<xmax>953</xmax>
			<ymax>749</ymax>
		</bndbox>
	</object>
	<object>
		<name>Bee</name>
		<pose>Front</pose>
		<truncated>0</truncated>
		<bndbox>
			<xmin>115</xmin>
			<ymin>929</ymin>
			<xmax>185</xmax>
			<ymax>990</ymax>
		</bndbox>
	</object>
	<object>
		<name>Bee</name>
		<pose>Front</pose>
		<truncated>0</truncated>
		<bndbox>
			<xmin>701</xmin>
			<ymin>675</ymin>
			<xmax>762</xmax>
			<ymax>745</ymax>
		</bndbox>
	</object>
	<object>
		<name>Bee</name>
		<pose>Front</pose>
		<truncated>0</truncated>
		<bndbox>
			<xmin>224</xmin>
			<ymin>173</ymin>
			<xmax>285</xmax>
			<ymax>243</ymax>
		</bndbox>
	</object>
	<object>
		<name>Bee</name>
		<pose>Front</pose>
		<truncated>0</truncated>
		<bndbox>
			<xmin>19</xmin>
			<ymin>181</ymin>
			<xmax>80</xmax>
			<ymax>251</ymax>
		</bndbox>
	</object>
	<object>
		<name>Bee</name>
		<pose>Front</pose>
		<truncated>0</truncated>
		<bndbox>
			<xmin>497</xmin>
			<ymin>832</ymin>
			<xmax>547</xmax>
			<ymax>903</ymax>
		</bndbox>
	</object>
	<object>
		<name>Bee</name>
		<pose>Front</pose>
		<truncated>0</truncated>
		<bndbox>
			<xmin>809</xmin>
			<ymin>613</ymin>
			<xmax>859</xmax>
			<ymax>684</ymax>
		</bndbox>
	</object>
	<object>
		<name>Bee</name>
		<pose>Front</pose>
		<truncated>0</truncated>
		<bndbox>
			<xmin>744</xmin>
			<ymin>185</ymin>
			<xmax>810</xmax>
			<ymax>266</ymax>
		</bndbox>
	</object>
	<object>
		<name>Bee</name>
		<pose>Front</pose>
		<truncated>0</truncated>
		<bndbox>
			<xmin>716</xmin>
			<ymin>364</ymin>
			<xmax>766</xmax>
			<ymax>435</ymax>
		</bndbox>
	</object>
</annotation>