<annotation>
	<folder>synthetic_data</folder>
	<filename>307.jpg</filename>
	<path>../dataset/synthetic_data/images/307.jpg</path>
	<source>
		<database>Source</database>
	</source>
	<segmented>0</segmented>
	<size>
		<width>1024</width>
		<height>768</height>
		<depth>3</depth>
	</size>
	<object>
		<name>Bee</name>
		<pose>Front</pose>
		<truncated>0</truncated>
		<bndbox>
			<xmin>150</xmin>
			<ymin>98</ymin>
			<xmax>194</xmax>
			<ymax>142</ymax>
		</bndbox>
	</object>
	<object>
		<name>Bee</name>
		<pose>Front</pose>
		<truncated>0</truncated>
		<bndbox>
			<xmin>767</xmin>
			<ymin>44</ymin>
			<xmax>828</xmax>
			<ymax>114</ymax>
		</bndbox>
	</object>
	<object>
		<name>Bee</name>
		<pose>Front</pose>
		<truncated>0</truncated>
		<bndbox>
			<xmin>493</xmin>
			<ymin>683</ymin>
			<xmax>559</xmax>
			<ymax>728</ymax>
		</bndbox>
	</object>
	<object>
		<name>Bee</name>
		<pose>Front</pose>
		<truncated>0</truncated>
		<bndbox>
			<xmin>153</xmin>
			<ymin>642</ymin>
			<xmax>246</xmax>
			<ymax>710</ymax>
		</bndbox>
	</object>
	<object>
		<name>Bee</name>
		<pose>Front</pose>
		<truncated>0</truncated>
		<bndbox>
			<xmin>715</xmin>
			<ymin>567</ymin>
			<xmax>862</xmax>
			<ymax>709</ymax>
		</bndbox>
	</object>
	<object>
		<name>Bee</name>
		<pose>Front</pose>
		<truncated>0</truncated>
		<bndbox>
			<xmin>390</xmin>
			<ymin>214</ymin>
			<xmax>501</xmax>
			<ymax>308</ymax>
		</bndbox>
	</object>
	<object>
		<name>Bee</name>
		<pose>Front</pose>
		<truncated>0</truncated>
		<bndbox>
			<xmin>78</xmin>
			<ymin>707</ymin>
			<xmax>130</xmax>
			<ymax>775</ymax>
		</bndbox>
	</object>
	<object>
		<name>Bee</name>
		<pose>Front</pose>
		<truncated>0</truncated>
		<bndbox>
			<xmin>450</xmin>
			<ymin>342</ymin>
			<xmax>502</xmax>
			<ymax>410</ymax>
		</bndbox>
	</object>
	<object>
		<name>Bee</name>
		<pose>Front</pose>
		<truncated>0</truncated>
		<bndbox>
			<xmin>106</xmin>
			<ymin>14</ymin>
			<xmax>174</xmax>
			<ymax>66</ymax>
		</bndbox>
	</object>
	<object>
		<name>Bee</name>
		<pose>Front</pose>
		<truncated>0</truncated>
		<bndbox>
			<xmin>856</xmin>
			<ymin>375</ymin>
			<xmax>938</xmax>
			<ymax>463</ymax>
		</bndbox>
	</object>
	<object>
		<name>Bee</name>
		<pose>Front</pose>
		<truncated>0</truncated>
		<bndbox>
			<xmin>321</xmin>
			<ymin>579</ymin>
			<xmax>413</xmax>
			<ymax>665</ymax>
		</bndbox>
	</object>
	<object>
		<name>Bee</name>
		<pose>Front</pose>
		<truncated>0</truncated>
		<bndbox>
			<xmin>268</xmin>
			<ymin>190</ymin>
			<xmax>350</xmax>
			<ymax>278</ymax>
		</bndbox>
	</object>
	<object>
		<name>Bee</name>
		<pose>Front</pose>
		<truncated>0</truncated>
		<bndbox>
			<xmin>120</xmin>
			<ymin>397</ymin>
			<xmax>208</xmax>
			<ymax>479</ymax>
		</bndbox>
	</object>
	<object>
		<name>Bee</name>
		<pose>Front</pose>
		<truncated>0</truncated>
		<bndbox>
			<xmin>946</xmin>
			<ymin>174</ymin>
			<xmax>1025</xmax>
			<ymax>256</ymax>
		</bndbox>
	</object>
	<object>
		<name>Bee</name>
		<pose>Front</pose>
		<truncated>0</truncated>
		<bndbox>
			<xmin>645</xmin>
			<ymin>598</ymin>
			<xmax>707</xmax>
			<ymax>651</ymax>
		</bndbox>
	</object>
	<object>
		<name>Bee</name>
		<pose>Front</pose>
		<truncated>0</truncated>
		<bndbox>
			<xmin>232</xmin>
			<ymin>588</ymin>
			<xmax>311</xmax>
			<ymax>664</ymax>
		</bndbox>
	</object>
	<object>
		<name>Bee</name>
		<pose>Front</pose>
		<truncated>0</truncated>
		<bndbox>
			<xmin>371</xmin>
			<ymin>121</ymin>
			<xmax>424</xmax>
			<ymax>183</ymax>
		</bndbox>
	</object>
	<object>
		<name>Bee</name>
		<pose>Front</pose>
		<truncated>0</truncated>
		<bndbox>
			<xmin>789</xmin>
			<ymin>504</ymin>
			<xmax>851</xmax>
			<ymax>557</ymax>
		</bndbox>
	</object>
	<object>
		<name>Bee</name>
		<pose>Front</pose>
		<truncated>0</truncated>
		<bndbox>
			<xmin>554</xmin>
			<ymin>538</ymin>
			<xmax>642</xmax>
			<ymax>621</ymax>
		</bndbox>
	</object>
	<object>
		<name>Bee</name>
		<pose>Front</pose>
		<truncated>0</truncated>
		<bndbox>
			<xmin>578</xmin>
			<ymin>108</ymin>
			<xmax>646</xmax>
			<ymax>191</ymax>
		</bndbox>
	</object>
	<object>
		<name>Bee</name>
		<pose>Front</pose>
		<truncated>0</truncated>
		<bndbox>
			<xmin>572</xmin>
			<ymin>386</ymin>
			<xmax>656</xmax>
			<ymax>459</ymax>
		</bndbox>
	</object>
</annotation>