<annotation>
	<folder>synthetic_data</folder>
	<filename>406.jpg</filename>
	<path>../dataset/synthetic_data/images/406.jpg</path>
	<source>
		<database>Source</database>
	</source>
	<segmented>0</segmented>
	<size>
		<width>1024</width>
		<height>1023</height>
		<depth>3</depth>
	</size>
	<object>
		<name>Bee</name>
		<pose>Front</pose>
		<truncated>0</truncated>
		<bndbox>
			<xmin>818</xmin>
			<ymin>73</ymin>
			<xmax>862</xmax>
			<ymax>117</ymax>
		</bndbox>
	</object>
	<object>
		<name>Bee</name>
		<pose>Front</pose>
		<truncated>0</truncated>
		<bndbox>
			<xmin>252</xmin>
			<ymin>952</ymin>
			<xmax>296</xmax>
			<ymax>996</ymax>
		</bndbox>
	</object>
	<object>
		<name>Bee</name>
		<pose>Front</pose>
		<truncated>0</truncated>
		<bndbox>
			<xmin>390</xmin>
			<ymin>35</ymin>
			<xmax>434</xmax>
			<ymax>79</ymax>
		</bndbox>
	</object>
	<object>
		<name>Bee</name>
		<pose>Front</pose>
		<truncated>0</truncated>
		<bndbox>
			<xmin>640</xmin>
			<ymin>131</ymin>
			<xmax>728</xmax>
			<ymax>213</ymax>
		</bndbox>
	</object>
	<object>
		<name>Bee</name>
		<pose>Front</pose>
		<truncated>0</truncated>
		<bndbox>
			<xmin>47</xmin>
			<ymin>418</ymin>
			<xmax>141</xmax>
			<ymax>529</ymax>
		</bndbox>
	</object>
	<object>
		<name>Bee</name>
		<pose>Front</pose>
		<truncated>0</truncated>
		<bndbox>
			<xmin>815</xmin>
			<ymin>185</ymin>
			<xmax>922</xmax>
			<ymax>300</ymax>
		</bndbox>
	</object>
	<object>
		<name>Bee</name>
		<pose>Front</pose>
		<truncated>0</truncated>
		<bndbox>
			<xmin>582</xmin>
			<ymin>764</ymin>
			<xmax>697</xmax>
			<ymax>871</ymax>
		</bndbox>
	</object>
	<object>
		<name>Bee</name>
		<pose>Front</pose>
		<truncated>0</truncated>
		<bndbox>
			<xmin>100</xmin>
			<ymin>691</ymin>
			<xmax>207</xmax>
			<ymax>806</ymax>
		</bndbox>
	</object>
	<object>
		<name>Bee</name>
		<pose>Front</pose>
		<truncated>0</truncated>
		<bndbox>
			<xmin>40</xmin>
			<ymin>195</ymin>
			<xmax>85</xmax>
			<ymax>261</ymax>
		</bndbox>
	</object>
	<object>
		<name>Bee</name>
		<pose>Front</pose>
		<truncated>0</truncated>
		<bndbox>
			<xmin>100</xmin>
			<ymin>971</ymin>
			<xmax>166</xmax>
			<ymax>1016</ymax>
		</bndbox>
	</object>
	<object>
		<name>Bee</name>
		<pose>Front</pose>
		<truncated>0</truncated>
		<bndbox>
			<xmin>500</xmin>
			<ymin>174</ymin>
			<xmax>566</xmax>
			<ymax>219</ymax>
		</bndbox>
	</object>
	<object>
		<name>Bee</name>
		<pose>Front</pose>
		<truncated>0</truncated>
		<bndbox>
			<xmin>325</xmin>
			<ymin>668</ymin>
			<xmax>416</xmax>
			<ymax>756</ymax>
		</bndbox>
	</object>
	<object>
		<name>Bee</name>
		<pose>Front</pose>
		<truncated>0</truncated>
		<bndbox>
			<xmin>239</xmin>
			<ymin>313</ymin>
			<xmax>309</xmax>
			<ymax>374</ymax>
		</bndbox>
	</object>
	<object>
		<name>Bee</name>
		<pose>Front</pose>
		<truncated>0</truncated>
		<bndbox>
			<xmin>925</xmin>
			<ymin>930</ymin>
			<xmax>986</xmax>
			<ymax>1000</ymax>
		</bndbox>
	</object>
</annotation>