<annotation>
	<folder>synthetic_data</folder>
	<filename>500.jpg</filename>
	<path>../dataset/synthetic_data/images/500.jpg</path>
	<source>
		<database>Source</database>
	</source>
	<segmented>0</segmented>
	<size>
		<width>1024</width>
		<height>768</height>
		<depth>3</depth>
	</size>
	<object>
		<name>Bee</name>
		<pose>Front</pose>
		<truncated>0</truncated>
		<bndbox>
			<xmin>923</xmin>
			<ymin>51</ymin>
			<xmax>968</xmax>
			<ymax>117</ymax>
		</bndbox>
	</object>
	<object>
		<name>Bee</name>
		<pose>Front</pose>
		<truncated>0</truncated>
		<bndbox>
			<xmin>288</xmin>
			<ymin>689</ymin>
			<xmax>357</xmax>
			<ymax>765</ymax>
		</bndbox>
	</object>
	<object>
		<name>Bee</name>
		<pose>Front</pose>
		<truncated>0</truncated>
		<bndbox>
			<xmin>376</xmin>
			<ymin>636</ymin>
			<xmax>444</xmax>
			<ymax>688</ymax>
		</bndbox>
	</object>
	<object>
		<name>Bee</name>
		<pose>Front</pose>
		<truncated>0</truncated>
		<bndbox>
			<xmin>63</xmin>
			<ymin>410</ymin>
			<xmax>175</xmax>
			<ymax>518</ymax>
		</bndbox>
	</object>
	<object>
		<name>Bee</name>
		<pose>Front</pose>
		<truncated>0</truncated>
		<bndbox>
			<xmin>56</xmin>
			<ymin>134</ymin>
			<xmax>203</xmax>
			<ymax>280</ymax>
		</bndbox>
	</object>
	<object>
		<name>Bee</name>
		<pose>Front</pose>
		<truncated>0</truncated>
		<bndbox>
			<xmin>498</xmin>
			<ymin>631</ymin>
			<xmax>548</xmax>
			<ymax>702</ymax>
		</bndbox>
	</object>
	<object>
		<name>Bee</name>
		<pose>Front</pose>
		<truncated>0</truncated>
		<bndbox>
			<xmin>277</xmin>
			<ymin>48</ymin>
			<xmax>348</xmax>
			<ymax>98</ymax>
		</bndbox>
	</object>
	<object>
		<name>Bee</name>
		<pose>Front</pose>
		<truncated>0</truncated>
		<bndbox>
			<xmin>559</xmin>
			<ymin>114</ymin>
			<xmax>721</xmax>
			<ymax>281</ymax>
		</bndbox>
	</object>
	<object>
		<name>Bee</name>
		<pose>Front</pose>
		<truncated>0</truncated>
		<bndbox>
			<xmin>384</xmin>
			<ymin>267</ymin>
			<xmax>551</xmax>
			<ymax>429</ymax>
		</bndbox>
	</object>
	<object>
		<name>Bee</name>
		<pose>Front</pose>
		<truncated>0</truncated>
		<bndbox>
			<xmin>724</xmin>
			<ymin>57</ymin>
			<xmax>764</xmax>
			<ymax>79</ymax>
		</bndbox>
	</object>
	<object>
		<name>Bee</name>
		<pose>Front</pose>
		<truncated>0</truncated>
		<bndbox>
			<xmin>624</xmin>
			<ymin>449</ymin>
			<xmax>648</xmax>
			<ymax>491</ymax>
		</bndbox>
	</object>
	<object>
		<name>Bee</name>
		<pose>Front</pose>
		<truncated>0</truncated>
		<bndbox>
			<xmin>147</xmin>
			<ymin>53</ymin>
			<xmax>191</xmax>
			<ymax>83</ymax>
		</bndbox>
	</object>
	<object>
		<name>Bee</name>
		<pose>Front</pose>
		<truncated>0</truncated>
		<bndbox>
			<xmin>800</xmin>
			<ymin>378</ymin>
			<xmax>840</xmax>
			<ymax>400</ymax>
		</bndbox>
	</object>
	<object>
		<name>Bee</name>
		<pose>Front</pose>
		<truncated>0</truncated>
		<bndbox>
			<xmin>223</xmin>
			<ymin>615</ymin>
			<xmax>306</xmax>
			<ymax>703</ymax>
		</bndbox>
	</object>
	<object>
		<name>Bee</name>
		<pose>Front</pose>
		<truncated>0</truncated>
		<bndbox>
			<xmin>291</xmin>
			<ymin>395</ymin>
			<xmax>352</xmax>
			<ymax>465</ymax>
		</bndbox>
	</object>
	<object>
		<name>Bee</name>
		<pose>Front</pose>
		<truncated>0</truncated>
		<bndbox>
			<xmin>657</xmin>
			<ymin>543</ymin>
			<xmax>718</xmax>
			<ymax>613</ymax>
		</bndbox>
	</object>
	<object>
		<name>Bee</name>
		<pose>Front</pose>
		<truncated>0</truncated>
		<bndbox>
			<xmin>930</xmin>
			<ymin>245</ymin>
			<xmax>1001</xmax>
			<ymax>323</ymax>
		</bndbox>
	</object>
	<object>
		<name>Bee</name>
		<pose>Front</pose>
		<truncated>0</truncated>
		<bndbox>
			<xmin>346</xmin>
			<ymin>3</ymin>
			<xmax>421</xmax>
			<ymax>85</ymax>
		</bndbox>
	</object>
	<object>
		<name>Bee</name>
		<pose>Front</pose>
		<truncated>0</truncated>
		<bndbox>
			<xmin>218</xmin>
			<ymin>194</ymin>
			<xmax>279</xmax>
			<ymax>264</ymax>
		</bndbox>
	</object>
</annotation>