<annotation>
	<folder>synthetic_data</folder>
	<filename>749.jpg</filename>
	<path>../dataset/synthetic_data/images/749.jpg</path>
	<source>
		<database>Source</database>
	</source>
	<segmented>0</segmented>
	<size>
		<width>1024</width>
		<height>683</height>
		<depth>3</depth>
	</size>
	<object>
		<name>Bee</name>
		<pose>Front</pose>
		<truncated>0</truncated>
		<bndbox>
			<xmin>13</xmin>
			<ymin>267</ymin>
			<xmax>53</xmax>
			<ymax>289</ymax>
		</bndbox>
	</object>
	<object>
		<name>Bee</name>
		<pose>Front</pose>
		<truncated>0</truncated>
		<bndbox>
			<xmin>615</xmin>
			<ymin>581</ymin>
			<xmax>709</xmax>
			<ymax>692</ymax>
		</bndbox>
	</object>
	<object>
		<name>Bee</name>
		<pose>Front</pose>
		<truncated>0</truncated>
		<bndbox>
			<xmin>254</xmin>
			<ymin>522</ymin>
			<xmax>356</xmax>
			<ymax>637</ymax>
		</bndbox>
	</object>
	<object>
		<name>Bee</name>
		<pose>Front</pose>
		<truncated>0</truncated>
		<bndbox>
			<xmin>491</xmin>
			<ymin>42</ymin>
			<xmax>584</xmax>
			<ymax>110</ymax>
		</bndbox>
	</object>
	<object>
		<name>Bee</name>
		<pose>Front</pose>
		<truncated>0</truncated>
		<bndbox>
			<xmin>564</xmin>
			<ymin>201</ymin>
			<xmax>604</xmax>
			<ymax>223</ymax>
		</bndbox>
	</object>
	<object>
		<name>Bee</name>
		<pose>Front</pose>
		<truncated>0</truncated>
		<bndbox>
			<xmin>108</xmin>
			<ymin>88</ymin>
			<xmax>148</xmax>
			<ymax>110</ymax>
		</bndbox>
	</object>
	<object>
		<name>Bee</name>
		<pose>Front</pose>
		<truncated>0</truncated>
		<bndbox>
			<xmin>638</xmin>
			<ymin>495</ymin>
			<xmax>660</xmax>
			<ymax>535</ymax>
		</bndbox>
	</object>
	<object>
		<name>Bee</name>
		<pose>Front</pose>
		<truncated>0</truncated>
		<bndbox>
			<xmin>2</xmin>
			<ymin>232</ymin>
			<xmax>42</xmax>
			<ymax>254</ymax>
		</bndbox>
	</object>
	<object>
		<name>Bee</name>
		<pose>Front</pose>
		<truncated>0</truncated>
		<bndbox>
			<xmin>25</xmin>
			<ymin>49</ymin>
			<xmax>65</xmax>
			<ymax>71</ymax>
		</bndbox>
	</object>
	<object>
		<name>Bee</name>
		<pose>Front</pose>
		<truncated>0</truncated>
		<bndbox>
			<xmin>8</xmin>
			<ymin>368</ymin>
			<xmax>61</xmax>
			<ymax>430</ymax>
		</bndbox>
	</object>
	<object>
		<name>Bee</name>
		<pose>Front</pose>
		<truncated>0</truncated>
		<bndbox>
			<xmin>442</xmin>
			<ymin>551</ymin>
			<xmax>495</xmax>
			<ymax>613</ymax>
		</bndbox>
	</object>
	<object>
		<name>Bee</name>
		<pose>Front</pose>
		<truncated>0</truncated>
		<bndbox>
			<xmin>472</xmin>
			<ymin>327</ymin>
			<xmax>525</xmax>
			<ymax>389</ymax>
		</bndbox>
	</object>
	<object>
		<name>Bee</name>
		<pose>Front</pose>
		<truncated>0</truncated>
		<bndbox>
			<xmin>276</xmin>
			<ymin>43</ymin>
			<xmax>320</xmax>
			<ymax>87</ymax>
		</bndbox>
	</object>
	<object>
		<name>Bee</name>
		<pose>Front</pose>
		<truncated>0</truncated>
		<bndbox>
			<xmin>180</xmin>
			<ymin>588</ymin>
			<xmax>224</xmax>
			<ymax>632</ymax>
		</bndbox>
	</object>
	<object>
		<name>Bee</name>
		<pose>Front</pose>
		<truncated>0</truncated>
		<bndbox>
			<xmin>665</xmin>
			<ymin>406</ymin>
			<xmax>709</xmax>
			<ymax>450</ymax>
		</bndbox>
	</object>
	<object>
		<name>Bee</name>
		<pose>Front</pose>
		<truncated>0</truncated>
		<bndbox>
			<xmin>868</xmin>
			<ymin>409</ymin>
			<xmax>942</xmax>
			<ymax>467</ymax>
		</bndbox>
	</object>
	<object>
		<name>Bee</name>
		<pose>Front</pose>
		<truncated>0</truncated>
		<bndbox>
			<xmin>523</xmin>
			<ymin>571</ymin>
			<xmax>591</xmax>
			<ymax>623</ymax>
		</bndbox>
	</object>
	<object>
		<name>Bee</name>
		<pose>Front</pose>
		<truncated>0</truncated>
		<bndbox>
			<xmin>597</xmin>
			<ymin>269</ymin>
			<xmax>665</xmax>
			<ymax>321</ymax>
		</bndbox>
	</object>
	<object>
		<name>Bee</name>
		<pose>Front</pose>
		<truncated>0</truncated>
		<bndbox>
			<xmin>590</xmin>
			<ymin>63</ymin>
			<xmax>697</xmax>
			<ymax>178</ymax>
		</bndbox>
	</object>
	<object>
		<name>Bee</name>
		<pose>Front</pose>
		<truncated>0</truncated>
		<bndbox>
			<xmin>428</xmin>
			<ymin>174</ymin>
			<xmax>543</xmax>
			<ymax>281</ymax>
		</bndbox>
	</object>
	<object>
		<name>Bee</name>
		<pose>Front</pose>
		<truncated>0</truncated>
		<bndbox>
			<xmin>101</xmin>
			<ymin>245</ymin>
			<xmax>331</xmax>
			<ymax>448</ymax>
		</bndbox>
	</object>
	<object>
		<name>Bee</name>
		<pose>Front</pose>
		<truncated>0</truncated>
		<bndbox>
			<xmin>763</xmin>
			<ymin>188</ymin>
			<xmax>954</xmax>
			<ymax>408</ymax>
		</bndbox>
	</object>
</annotation>